immich_migrator/__init__.py
immich_migrator/__main__.py
immich_migrator/py.typed
immich_migrator/cli/__init__.py
immich_migrator/cli/app.py
immich_migrator/cli/tui.py
immich_migrator/lib/__init__.py
immich_migrator/lib/logging.py
immich_migrator/lib/progress.py
immich_migrator/models/__init__.py
immich_migrator/models/album.py
immich_migrator/models/asset.py
immich_migrator/models/config.py
immich_migrator/models/state.py
immich_migrator/services/__init__.py
immich_migrator/services/downloader.py
immich_migrator/services/exif_injector.py
immich_migrator/services/immich_client.py
immich_migrator/services/state_manager.py
immich_migrator/services/uploader.py
immich_migrator-0.4.7.dist-info/METADATA
immich_migrator-0.4.7.dist-info/WHEEL
immich_migrator-0.4.7.dist-info/entry_points.txt
immich_migrator-0.4.7.dist-info/licenses/LICENSE
immich_migrator-0.4.7.dist-info/RECORD
