Metadata-Version: 2.4
Name: immich-migrator
Version: 0.4.7
Summary: CLI tool for migrating photo albums between Immich servers
Project-URL: Homepage, https://github.com/kallegrens/immich-migrator
Project-URL: Repository, https://github.com/kallegrens/immich-migrator
Project-URL: Issues, https://github.com/kallegrens/immich-migrator/issues
Project-URL: Changelog, https://github.com/kallegrens/immich-migrator/blob/main/CHANGELOG.md
Author-email: Karl Lundgren <k.github@lundgrens.net>
License: AGPL-3.0-or-later
License-File: LICENSE
Keywords: backup,cli,immich,migration,photo-management,self-hosted
Classifier: Development Status :: 3 - Alpha
Classifier: Intended Audience :: End Users/Desktop
Classifier: Intended Audience :: System Administrators
Classifier: License :: OSI Approved :: GNU Affero General Public License v3
Classifier: Operating System :: OS Independent
Classifier: Programming Language :: Python :: 3
Classifier: Programming Language :: Python :: 3.11
Classifier: Programming Language :: Python :: 3.12
Classifier: Programming Language :: Python :: 3.13
Classifier: Topic :: System :: Archiving :: Backup
Classifier: Topic :: Utilities
Classifier: Typing :: Typed
Requires-Python: >=3.11
Requires-Dist: httpx>=0.27.0
Requires-Dist: loguru>=0.7.0
Requires-Dist: pydantic>=2.6.0
Requires-Dist: pyexiftool>=0.5.0
Requires-Dist: questionary>=2.0.0
Requires-Dist: requests>=2.32.5
Requires-Dist: rich>=13.7.0
Requires-Dist: tenacity>=8.2.0
Requires-Dist: typer>=0.12.0
